diffpose/__init__.py
diffpose/_modidx.py
diffpose/calibration.py
diffpose/deepfluoro.py
diffpose/jacobians.py
diffpose/ljubljana.py
diffpose/metrics.py
diffpose/registration.py
diffpose/visualization.py
diffpose-0.0.1.dist-info/LICENSE
diffpose-0.0.1.dist-info/METADATA
diffpose-0.0.1.dist-info/WHEEL
diffpose-0.0.1.dist-info/entry_points.txt
diffpose-0.0.1.dist-info/top_level.txt
diffpose-0.0.1.dist-info/RECORD
