Metadata-Version: 2.1
Name: diffpose
Version: 0.0.1
Summary: Patient-specific intraoperative 2D/3D registration via differentiable rendering
Home-page: https://github.com/eigenvivek/DiffPose
Author: Vivek Gopalakrihsnan
Author-email: vivekg@mit.edu
License: MIT License
Keywords: nbdev jupyter notebook python
Classifier: Development Status :: 4 - Beta
Classifier: Intended Audience :: Developers
Classifier: Natural Language :: English
Classifier: Programming Language :: Python :: 3.7
Classifier: Programming Language :: Python :: 3.8
Classifier: Programming Language :: Python :: 3.9
Classifier: Programming Language :: Python :: 3.10
Classifier: License :: OSI Approved :: MIT License
Requires-Python: >=3.7
License-File: LICENSE
Requires-Dist: diffdrr
Requires-Dist: h5py
Requires-Dist: scikit-image
Requires-Dist: seaborn
Requires-Dist: torch
Requires-Dist: torchvision
Requires-Dist: pytorch3d
Requires-Dist: timm
Requires-Dist: pytorch-transformers
Requires-Dist: pytorchse3
Requires-Dist: torchmetrics
Requires-Dist: tqdm
Requires-Dist: beartype
Requires-Dist: jaxtyping
Provides-Extra: dev
Requires-Dist: jupyterlab-code-formatter ; extra == 'dev'
Requires-Dist: black ; extra == 'dev'
Requires-Dist: flake8 ; extra == 'dev'
Requires-Dist: isort ; extra == 'dev'
Requires-Dist: nbdev ; extra == 'dev'
Requires-Dist: ipykernel ; extra == 'dev'
Requires-Dist: jupyter-server-proxy ; extra == 'dev'
